popsynch/__init__.py
popsynch/popsynch.py
popsynch-0.4.dist-info/LICENSE.txt
popsynch-0.4.dist-info/METADATA
popsynch-0.4.dist-info/WHEEL
popsynch-0.4.dist-info/top_level.txt
popsynch-0.4.dist-info/RECORD
