Metadata-Version: 2.1
Name: popsynch
Version: 0.4
Summary: A pure Python package for computing the synchrony of population distributions in compact metric spaces.
Home-page: https://gitlab.com/biochron/popsynch
Download-URL: https://gitlab.com/biochron/popsynch/-/archive/1.0.0/popsynch-1.0.tar.gz
Author: Francis C. Motta
Author-email: fmotta@fau.edu
License: MIT
Keywords: Synchrony,Synchronization,Frechet Variance,Wasserstein Distance,Optimal Transport
Classifier: Programming Language :: Python :: 3
Classifier: License :: OSI Approved :: MIT License
Classifier: Operating System :: OS Independent
Classifier: Development Status :: 4 - Beta
Requires-Python: >=3.12
License-File: LICENSE.txt
Requires-Dist: scipy>=1.12
Requires-Dist: numpy>=1.26.3
Provides-Extra: notebooks
Requires-Dist: matplotlib>=3.8.2; extra == "notebooks"
Requires-Dist: pandas>=2.2; extra == "notebooks"
Requires-Dist: jupyter>=1.0.0; extra == "notebooks"
